oldfolder/__init__.py
oldfolder/oldfolder.py
oldfolder-0.1.1.dist-info/LICENSE
oldfolder-0.1.1.dist-info/METADATA
oldfolder-0.1.1.dist-info/WHEEL
oldfolder-0.1.1.dist-info/entry_points.txt
oldfolder-0.1.1.dist-info/top_level.txt
oldfolder-0.1.1.dist-info/RECORD
