Metadata-Version: 2.1
Name: oldfolder
Version: 0.1.1
Summary: Spring cleans a file directory by storing away its old subdirectories.
Home-page: https://github.com/jonboland/oldfolder
Author: Jon Boland
Author-email: jon@codeclear.co.uk
License: UNKNOWN
Platform: UNKNOWN
Classifier: Programming Language :: Python :: 3
Classifier: License :: OSI Approved :: BSD License
Classifier: Operating System :: OS Independent
Requires-Python: >=3.6
